sip_message_client/__init__.py
sip_message_client/core/sip_message.py
sip_message_client/core/sip_server_response.py
sip_message_client-0.1.2.dist-info/METADATA
sip_message_client-0.1.2.dist-info/WHEEL
sip_message_client-0.1.2.dist-info/RECORD
