Metadata-Version: 2.1
Name: sip-message-client
Version: 0.1.2
Summary: simple python socket app to send sms via sip server
Author: Przemyslaw Bubas
Author-email: bprzemys@cisco.com
Requires-Python: >=3.10,<4.0
Classifier: Programming Language :: Python :: 3
Classifier: Programming Language :: Python :: 3.10
Classifier: Programming Language :: Python :: 3.11
